diamond/__init__.py
diamond/e.py
diamond_e-0.0.2.dist-info/LICENSE
diamond_e-0.0.2.dist-info/METADATA
diamond_e-0.0.2.dist-info/WHEEL
diamond_e-0.0.2.dist-info/top_level.txt
diamond_e-0.0.2.dist-info/RECORD
